README.rst
setup.py
guazi_crawler_lib/__init__.py
guazi_crawler_lib/decorators.py
guazi_crawler_lib.egg-info/PKG-INFO
guazi_crawler_lib.egg-info/SOURCES.txt
guazi_crawler_lib.egg-info/dependency_links.txt
guazi_crawler_lib.egg-info/top_level.txt